cami_amber/__init__.py
cami_amber/amber_html.py
cami_amber/binning_classes.py
cami_amber/evaluate.py
cami_amber/plot_by_genome.py
cami_amber/plots.py
cami_amber/precision_recall_per_bin.py
cami_amber/unifrac_distance.py
cami_amber/utils/EMDUnifrac.py
cami_amber/utils/ProfilingTools.py
cami_amber/utils/__init__.py
cami_amber/utils/add_length_column.py
cami_amber/utils/argparse_parents.py
cami_amber/utils/convert_fasta_bins_to_biobox_format.py
cami_amber/utils/labels.py
cami_amber/utils/load_data.py
cami_amber/utils/load_ncbi_taxinfo.py
cami_amber-2.0.7.data/scripts/amber.py
cami_amber-2.0.7.data/scripts/setup.py
cami_amber-2.0.7.data/scripts/version.py
cami_amber-2.0.7.dist-info/LICENSE
cami_amber-2.0.7.dist-info/METADATA
cami_amber-2.0.7.dist-info/WHEEL
cami_amber-2.0.7.dist-info/top_level.txt
cami_amber-2.0.7.dist-info/RECORD
